django_inline_media-1.4.2.dist-info/DESCRIPTION.rst
django_inline_media-1.4.2.dist-info/METADATA
django_inline_media-1.4.2.dist-info/RECORD
django_inline_media-1.4.2.dist-info/WHEEL
django_inline_media-1.4.2.dist-info/metadata.json
django_inline_media-1.4.2.dist-info/top_level.txt
inline_media/__init__.py
inline_media/admin.py
inline_media/apps.py
inline_media/fields.py
inline_media/models.py
inline_media/parser.py
inline_media/sorl_backends.py
inline_media/urls.py
inline_media/utils.py
inline_media/views.py
inline_media/widgets.py
inline_media/conf/__init__.py
inline_media/conf/defaults.py
inline_media/migrations/0001_initial.py
inline_media/migrations/0002_auto_20150825_0829.py
inline_media/migrations/0003_auto_20170218_1532.py
inline_media/migrations/__init__.py
inline_media/static/admin/inline_media/js/inlines.js
inline_media/static/admin/inline_media/js/picture.js
inline_media/static/admin/inline_media/js/pictureset.js
inline_media/static/admin/inline_media/js/wysihtml5/insertInlineMedia.js
inline_media/static/inline_media/css/inline_media.css
inline_media/static/inline_media/js/inline_media.js
inline_media/static/prettyphoto-3.1.3/css/prettyPhoto.css
inline_media/static/prettyphoto-3.1.3/images/.DS_Store
inline_media/static/prettyphoto-3.1.3/images/fullscreen/.DS_Store
inline_media/static/prettyphoto-3.1.3/images/fullscreen/1.jpg
inline_media/static/prettyphoto-3.1.3/images/fullscreen/2.jpg
inline_media/static/prettyphoto-3.1.3/images/fullscreen/3.jpg
inline_media/static/prettyphoto-3.1.3/images/fullscreen/4.jpg
inline_media/static/prettyphoto-3.1.3/images/fullscreen/5.jpg
inline_media/static/prettyphoto-3.1.3/images/fullscreen/6.jpg
inline_media/static/prettyphoto-3.1.3/images/fullscreen/high.gif
inline_media/static/prettyphoto-3.1.3/images/fullscreen/huge.gif
inline_media/static/prettyphoto-3.1.3/images/fullscreen/wide.gif
inline_media/static/prettyphoto-3.1.3/images/prettyPhoto/dark_rounded/btnNext.png
inline_media/static/prettyphoto-3.1.3/images/prettyPhoto/dark_rounded/btnPrevious.png
inline_media/static/prettyphoto-3.1.3/images/prettyPhoto/dark_rounded/contentPattern.png
inline_media/static/prettyphoto-3.1.3/images/prettyPhoto/dark_rounded/default_thumbnail.gif
