Metadata-Version: 1.1
Name: django-inline-media
Version: 1.4.2
Summary: django-inline-media allows insertion of inline media objects in text fields.
Home-page: http://pypi.python.org/pypi/django-inline-media/
Author: Daniel Rus Morales
Author-email: mbox@danir.us
License: MIT
Keywords: django apps
Platform: UNKNOWN
Classifier: Development Status :: 5 - Production/Stable
Classifier: Environment :: Web Environment
Classifier: Intended Audience :: Developers
Classifier: License :: OSI Approved :: MIT License
Classifier: Operating System :: OS Independent
Classifier: Programming Language :: Python
Classifier: Programming Language :: Python :: 3
Classifier: Framework :: Django
Classifier: Natural Language :: English
Classifier: Topic :: Internet :: WWW/HTTP :: Dynamic Content :: News/Diary
